Metadata-Version: 2.1
Name: classesGit
Version: 1.0.2
Summary: Classes for scripts
Home-page: UNKNOWN
Author: Bogdan Marcu
Author-email: bogdan.marcu@tss-yonder.com
License: UNKNOWN
Platform: UNKNOWN
